multiauthsample/__init__.py
multiauthsample/api_helper.py
multiauthsample/configuration.py
multiauthsample/multiauthsample_client.py
multiauthsample/controllers/__init__.py
multiauthsample/controllers/authentication_controller.py
multiauthsample/controllers/base_controller.py
multiauthsample/controllers/o_auth_authorization_controller.py
multiauthsample/exceptions/__init__.py
multiauthsample/exceptions/api_exception.py
multiauthsample/exceptions/o_auth_provider_exception.py
multiauthsample/http/__init__.py
multiauthsample/http/http_call_back.py
multiauthsample/http/http_method_enum.py
multiauthsample/http/http_request.py
multiauthsample/http/http_response.py
multiauthsample/http/auth/__init__.py
multiauthsample/http/auth/api_header.py
multiauthsample/http/auth/api_key.py
multiauthsample/http/auth/basic_auth.py
multiauthsample/http/auth/custom_auth.py
multiauthsample/http/auth/o_auth_acg.py
multiauthsample/http/auth/o_auth_bearer_token.py
multiauthsample/http/auth/o_auth_ccg.py
multiauthsample/http/auth/o_auth_ropcg.py
multiauthsample/models/__init__.py
multiauthsample/models/o_auth_provider_error_enum.py
multiauthsample/models/o_auth_scope_o_auth_acg_enum.py
multiauthsample/models/o_auth_token.py
multiauthsample/models/service_status.py
multiauthsample/models/suite_code_enum.py
multiauthsample/models/user.py
multiauthsample/utilities/__init__.py
multiauthsample/utilities/file_wrapper.py
multi_auth_project_sdk-1.0.0.dist-info/LICENSE
multi_auth_project_sdk-1.0.0.dist-info/METADATA
multi_auth_project_sdk-1.0.0.dist-info/WHEEL
multi_auth_project_sdk-1.0.0.dist-info/top_level.txt
multi_auth_project_sdk-1.0.0.dist-info/RECORD
