Metadata-Version: 2.1
Name: multi-auth-project-sdk
Version: 1.0.0
Summary: this is testingpackage please ignore
Author-email: Subtain <syed.subtain@apimatic.io>
Project-URL: Documentation, https://apimatic.io
Requires-Python: >=3.7
License-File: LICENSE
Requires-Dist: apimatic-core ~=0.2.0
Requires-Dist: apimatic-core-interfaces ~=0.1.0
Requires-Dist: apimatic-requests-client-adapter ~=0.1.0
Requires-Dist: python-dateutil ~=2.8.1
Requires-Dist: enum34 >=1.1.10,~=1.1
Requires-Dist: deprecation ~=2.1
Provides-Extra: testutils
Requires-Dist: pytest >=7.2.2 ; extra == 'testutils'
